vnn/__init__.py
vnn/classic.py
vnn/dropout.py
vnn/functional.py
vnn/variational.py
vnn-0.2.0.dist-info/METADATA
vnn-0.2.0.dist-info/WHEEL
vnn-0.2.0.dist-info/licenses/LICENSE
vnn-0.2.0.dist-info/RECORD
