Metadata-Version: 2.1
Name: vnn
Version: 0.2.0
Summary: Variational Neural Networks
Project-URL: Homepage, https://github.com/iliiliiliili/variational-nn-pytorch
Project-URL: Bug Tracker, https://github.com/iliiliiliili/variational-nn-pytorch/issues
Author-email: "Illia Oleksiienko, Dat Thanh Tran, Alexandros Iosifidis" <io@ece.au.dk>
License-File: LICENSE
Classifier: License :: OSI Approved :: Apache Software License
Classifier: Operating System :: OS Independent
Classifier: Programming Language :: Python :: 3
Requires-Python: >=3.7
